conllu/__init__.py
conllu/exceptions.py
conllu/models.py
conllu/parser.py
conllu/py.typed
conllu/serializer.py
conllu-6.0.0.dist-info/LICENSE
conllu-6.0.0.dist-info/METADATA
conllu-6.0.0.dist-info/WHEEL
conllu-6.0.0.dist-info/top_level.txt
conllu-6.0.0.dist-info/RECORD
