Metadata-Version: 2.1
Name: conllu
Version: 6.0.0
Summary: CoNLL-U Parser parses a CoNLL-U formatted string into a nested python dictionary
Author-email: Emil Stenström <emil@emilstenstrom.se>
License: The MIT License (MIT)
Project-URL: Homepage, https://github.com/EmilStenstrom/conllu/
Keywords: conllu,conll,conll-u,parser,nlp
Classifier: Programming Language :: Python
Classifier: Programming Language :: Python :: 3
Classifier: Programming Language :: Python :: 3 :: Only
Classifier: Programming Language :: Python :: 3.8
Classifier: Programming Language :: Python :: 3.9
Classifier: Programming Language :: Python :: 3.10
Classifier: Programming Language :: Python :: 3.11
Classifier: Programming Language :: Python :: 3.12
Classifier: Operating System :: OS Independent
Requires-Python: >=3.8
License-File: LICENSE
Provides-Extra: test
Requires-Dist: tox; extra == "test"
